user_utils/__init__.py
user_utils/config.py
user_utils/crud.py
user_utils/database.py
user_utils/models.py
user_utils/schemas.py
user_utils/validators.py
user_utils_vpetrov-0.1.0.dist-info/METADATA
user_utils_vpetrov-0.1.0.dist-info/WHEEL
user_utils_vpetrov-0.1.0.dist-info/top_level.txt
user_utils_vpetrov-0.1.0.dist-info/RECORD
