Metadata-Version: 2.1
Name: user_utils_vpetrov
Version: 0.1.0
Requires-Dist: fastapi
Requires-Dist: pydantic
Requires-Dist: sqlalchemy
Requires-Dist: alembic
Requires-Dist: email-validator
Requires-Dist: python-dateutil
